{"nhits": 1, "parameters": {"dataset": "blue-bike-deelfietsen-gent-sint-pieters-st-denijslaan", "rows": 10, "start": 0, "format": "json", "timezone": "UTC"}, "records": [{"datasetid": "blue-bike-deelfietsen-gent-sint-pieters-st-denijslaan", "recordid": "719d957c8b4e48a1c3604099b18eb9c9af1a7a64", "fields": {"name": "Station Gent-St. P. (St.-Denijslaan)", "type": "1", "last_seen": "2022-12-10T03:18:26+00:00", "bikes_in_use": 24, "longitude": "3.709667000000", "id": 73, "geopoint": [51.034889, 3.709667], "latitude": "51.034889000000", "bikes_available": 31}, "geometry": {"type": "Point", "coordinates": [3.709667, 51.034889]}, "record_timestamp": "2022-12-10T02:25:13.522Z"}]}